{
  "$schema": "http://json-schema.org/draft-07/schema#",
  "$id": "grimoire:schemas/08-revision/critical-theory/narrative-ethics.schema.json",
  "title": "Grimoire · Narrative Ethics",
  "description": "Extraction schema for narrative-ethics.md. Fields map to **Label:** fill-ins, tables, and checkbox groups in the template. Mark fields with x-source-required: true when the value should cite a source passage.",
  "type": "object",
  "properties": {
    "_source_text": {
      "$ref": "grimoire:base#/$defs/sourceTextMeta",
      "description": "Metadata about the source text being analyzed (fill in when using this template for book analysis).",
      "x-analysis-only": true
    },
    "character_rows": {
      "type": "array",
      "description": "Table with columns: Character, Interiority access (full / partial / gesture / none), Social position, Narrative function, Is interiority distribution just?",
      "items": {
        "type": "object",
        "properties": {
          "character": {
            "type": "string",
            "description": "Character",
            "x-source-required": false
          },
          "interiority_access_full_partial_gesture_none": {
            "type": "string",
            "description": "Interiority access (full / partial / gesture / none)",
            "x-source-required": false
          },
          "social_position": {
            "type": "string",
            "description": "Social position",
            "x-source-required": false
          },
          "narrative_function": {
            "type": "string",
            "description": "Narrative function",
            "x-source-required": false
          },
          "is_interiority_distribution_just": {
            "type": "string",
            "description": "Is interiority distribution just?",
            "x-source-required": false
          }
        }
      },
      "x-source-required": false
    },
    "_annotations": {
      "$ref": "grimoire:base#/$defs/annotations",
      "description": "Extracted <!-- key:value --> annotation tags."
    }
  },
  "x-grimoire-template": "08-revision/critical-theory/narrative-ethics.md"
}
